[
  {
    "stock_code": "0005.HK",
    "stock_name": "汇丰银行",
    "total_return": 0.20865376649450496,
    "annual_return": 0.0721272279240264,
    "final_capital": 120865.3766494505,
    "sharpe_ratio": 0.53892878892465,
    "sortino_ratio": 0.8340724867705239,
    "max_drawdown": -0.08613133365239233,
    "win_rate": 0.29545454545454547,
    "total_trades": 44,
    "winning_trades_count": 13,
    "losing_trades_count": 9,
    "benchmark_return": 1.6163410301953824,
    "benchmark_annual_return": 0.5587351709317371,
    "benchmark_sharpe": 1.5327419021360196,
    "benchmark_max_drawdown": -0.22107550244432375,
    "excess_return": 0,
    "information_ratio": -1.4456098399480448,
    "data_points": 730,
    "backtest_date": "2026-03-01 13:12:48"
  },
  {
    "stock_code": "0012.HK",
    "stock_name": "恒基地产",
    "total_return": 0.26649413093490976,
    "annual_return": 0.09212142797749967,
    "final_capital": 126649.41309349098,
    "sharpe_ratio": 0.49470565577263387,
    "sortino_ratio": 0.7020124305832719,
    "max_drawdown": -0.15589396523075513,
    "win_rate": 0.2391304347826087,
    "total_trades": 92,
    "winning_trades_count": 22,
    "losing_trades_count": 24,
    "benchmark_return": 0.277117117117117,
    "benchmark_annual_return": 0.09579357134912686,
    "benchmark_sharpe": 0.37087420798207116,
    "benchmark_max_drawdown": -0.32062391681109165,
    "excess_return": 0,
    "information_ratio": -0.13132150770891507,
    "data_points": 730,
    "backtest_date": "2026-03-01 13:12:48"
  },
  {
    "stock_code": "0016.HK",
    "stock_name": "新鸿基地产",
    "total_return": 0.054135090580505495,
    "annual_return": 0.018713364645113008,
    "final_capital": 105413.50905805055,
    "sharpe_ratio": 0.03297681153814204,
    "sortino_ratio": 0.04038934178683672,
    "max_drawdown": -0.11453495026661854,
    "win_rate": 0.25806451612903225,
    "total_trades": 62,
    "winning_trades_count": 16,
    "losing_trades_count": 15,
    "benchmark_return": 0.39846743295019144,
    "benchmark_annual_return": 0.13774182867414025,
    "benchmark_sharpe": 0.5071259496869756,
    "benchmark_max_drawdown": -0.4059674502712473,
    "excess_return": 0,
    "information_ratio": -0.5382331333896864,
    "data_points": 730,
    "backtest_date": "2026-03-01 13:12:48"
  },
  {
    "stock_code": "0388.HK",
    "stock_name": "香港交易所",
    "total_return": 0.6492655750200109,
    "annual_return": 0.22443748272296674,
    "final_capital": 164926.5575020011,
    "sharpe_ratio": 1.1298345367057814,
    "sortino_ratio": 2.2109500853374624,
    "max_drawdown": -0.08208417759826439,
    "win_rate": 0.32894736842105265,
    "total_trades": 76,
    "winning_trades_count": 25,
    "losing_trades_count": 13,
    "benchmark_return": 0.29161528976572154,
    "benchmark_annual_return": 0.10080528535111362,
    "benchmark_sharpe": 0.37152452145152837,
    "benchmark_max_drawdown": -0.3843947217441192,
    "excess_return": 0,
    "information_ratio": 0.12915865708677296,
    "data_points": 730,
    "backtest_date": "2026-03-01 13:12:48"
  },
  {
    "stock_code": "0700.HK",
    "stock_name": "腾讯控股",
    "total_return": 0.5759108650170092,
    "annual_return": 0.19908029901822538,
    "final_capital": 157591.08650170092,
    "sharpe_ratio": 0.8824503472018609,
    "sortino_ratio": 1.3054237799700315,
    "max_drawdown": -0.12719680179961368,
    "win_rate": 0.3269230769230769,
    "total_trades": 52,
    "winning_trades_count": 17,
    "losing_trades_count": 9,
    "benchmark_return": 0.502320185614849,
    "benchmark_annual_return": 0.17364154564463916,
    "benchmark_sharpe": 0.540331220699289,
    "benchmark_max_drawdown": -0.32457496136012237,
    "excess_return": 0,
    "information_ratio": -0.07125323865233625,
    "data_points": 730,
    "backtest_date": "2026-03-01 13:12:48"
  },
  {
    "stock_code": "0728.HK",
    "stock_name": "中国电信",
    "total_return": -0.03326737450648914,
    "annual_return": -0.011499833162736985,
    "final_capital": 96673.26254935109,
    "sharpe_ratio": -0.13722404128988397,
    "sortino_ratio": -0.19101163248406577,
    "max_drawdown": -0.2307063166632705,
    "win_rate": 0.2543859649122807,
    "total_trades": 114,
    "winning_trades_count": 29,
    "losing_trades_count": 28,
    "benchmark_return": 0.11160714285714275,
    "benchmark_annual_return": 0.03858024691358021,
    "benchmark_sharpe": 0.19312644301218512,
    "benchmark_max_drawdown": -0.2738095238095241,
    "excess_return": 0,
    "information_ratio": -0.3347434481928983,
    "data_points": 730,
    "backtest_date": "2026-03-01 13:12:48"
  },
  {
    "stock_code": "0883.HK",
    "stock_name": "中国海洋石油",
    "total_return": 0.14020967473360535,
    "annual_return": 0.0484675418832216,
    "final_capital": 114020.96747336054,
    "sharpe_ratio": 0.2966810455924749,
    "sortino_ratio": 0.4004488541633727,
    "max_drawdown": -0.16676060931612532,
    "win_rate": 0.3148148148148148,
    "total_trades": 54,
    "winning_trades_count": 17,
    "losing_trades_count": 10,
    "benchmark_return": 1.0960264900662253,
    "benchmark_annual_return": 0.3788733545907939,
    "benchmark_sharpe": 0.9470556219722753,
    "benchmark_max_drawdown": -0.33531914893617015,
    "excess_return": 0,
    "information_ratio": -0.9020852330574163,
    "data_points": 730,
    "backtest_date": "2026-03-01 13:12:48"
  },
  {
    "stock_code": "0939.HK",
    "stock_name": "建设银行",
    "total_return": 0.5938499551024108,
    "annual_return": 0.20528146596132718,
    "final_capital": 159384.99551024107,
    "sharpe_ratio": 1.4083389221358713,
    "sortino_ratio": 2.3265584821118943,
    "max_drawdown": -0.09974876560382542,
    "win_rate": 0.27906976744186046,
    "total_trades": 86,
    "winning_trades_count": 24,
    "losing_trades_count": 19,
    "benchmark_return": 0.6012024048096192,
    "benchmark_annual_return": 0.20782305351443625,
    "benchmark_sharpe": 0.7145294634706529,
    "benchmark_max_drawdown": -0.28596802841918284,
    "excess_return": 0,
    "information_ratio": -0.11742106232488093,
    "data_points": 730,
    "backtest_date": "2026-03-01 13:12:48"
  },
  {
    "stock_code": "0941.HK",
    "stock_name": "中国移动",
    "total_return": -0.02534082038849345,
    "annual_return": -0.008759789763923661,
    "final_capital": 97465.91796115066,
    "sharpe_ratio": -0.34339115053645813,
    "sortino_ratio": -0.4758321572178166,
    "max_drawdown": -0.1796742240326179,
    "win_rate": 0.19117647058823528,
    "total_trades": 68,
    "winning_trades_count": 13,
    "losing_trades_count": 21,
    "benchmark_return": 0.22282189668465696,
    "benchmark_annual_return": 0.07702485317494315,
    "benchmark_sharpe": 0.37518839767919554,
    "benchmark_max_drawdown": -0.13669064748201418,
    "excess_return": 0,
    "information_ratio": -0.5886594578364844,
    "data_points": 730,
    "backtest_date": "2026-03-01 13:12:48"
  },
  {
    "stock_code": "0981.HK",
    "stock_name": "中芯国际",
    "total_return": 2.0317926545969134,
    "annual_return": 0.7023480781322663,
    "final_capital": 303179.26545969135,
    "sharpe_ratio": 1.5157035679545545,
    "sortino_ratio": 2.9590619271588907,
    "max_drawdown": -0.14525003898117447,
    "win_rate": 0.2894736842105263,
    "total_trades": 76,
    "winning_trades_count": 22,
    "losing_trades_count": 16,
    "benchmark_return": 3.223602484472049,
    "benchmark_annual_return": 1.1143317230273748,
    "benchmark_sharpe": 1.1099444708209003,
    "benchmark_max_drawdown": -0.4523437500000002,
    "excess_return": 0,
    "information_ratio": -0.4758314627463705,
    "data_points": 730,
    "backtest_date": "2026-03-01 13:12:48"
  },
  {
    "stock_code": "1088.HK",
    "stock_name": "中国神华",
    "total_return": 0.20009220523150725,
    "annual_return": 0.06916767588249632,
    "final_capital": 120009.22052315073,
    "sharpe_ratio": 0.46093972789760906,
    "sortino_ratio": 0.6734771388841024,
    "max_drawdown": -0.09445404007110772,
    "win_rate": 0.31666666666666665,
    "total_trades": 60,
    "winning_trades_count": 19,
    "losing_trades_count": 11,
    "benchmark_return": 0.7876739562624256,
    "benchmark_annual_return": 0.27228235525120886,
    "benchmark_sharpe": 0.7654694673824836,
    "benchmark_max_drawdown": -0.2928039702233253,
    "excess_return": 0,
    "information_ratio": -0.6430820260005695,
    "data_points": 730,
    "backtest_date": "2026-03-01 13:12:48"
  },
  {
    "stock_code": "1109.HK",
    "stock_name": "华润置地",
    "total_return": 0.6167218317030088,
    "annual_return": 0.21318779367511412,
    "final_capital": 161672.18317030088,
    "sharpe_ratio": 1.0179523012168452,
    "sortino_ratio": 1.6936868239719542,
    "max_drawdown": -0.09707167071059333,
    "win_rate": 0.3333333333333333,
    "total_trades": 60,
    "winning_trades_count": 20,
    "losing_trades_count": 10,
    "benchmark_return": -0.08546762589928054,
    "benchmark_annual_return": -0.029544364508393272,
    "benchmark_sharpe": 0.08160899130937184,
    "benchmark_max_drawdown": -0.5153358681875787,
    "excess_return": 0,
    "information_ratio": 0.32380554109565113,
    "data_points": 730,
    "backtest_date": "2026-03-01 13:12:48"
  },
  {
    "stock_code": "1138.HK",
    "stock_name": "中远海能",
    "total_return": 0.8660644517778102,
    "annual_return": 0.29938030431825535,
    "final_capital": 186606.44517778102,
    "sharpe_ratio": 0.7604920960815107,
    "sortino_ratio": 1.1684452509103496,
    "max_drawdown": -0.4643538065579507,
    "win_rate": 0.27,
    "total_trades": 100,
    "winning_trades_count": 27,
    "losing_trades_count": 23,
    "benchmark_return": 1.0203862660944203,
    "benchmark_annual_return": 0.3527261166746144,
    "benchmark_sharpe": 0.6989563907581612,
    "benchmark_max_drawdown": -0.5511945392491465,
    "excess_return": 0,
    "information_ratio": -0.25899927808616124,
    "data_points": 730,
    "backtest_date": "2026-03-01 13:12:48"
  },
  {
    "stock_code": "1288.HK",
    "stock_name": "农业银行",
    "total_return": 0.7756035734831119,
    "annual_return": 0.2681098772534214,
    "final_capital": 177560.3573483112,
    "sharpe_ratio": 1.2029195079498296,
    "sortino_ratio": 1.6002366989273045,
    "max_drawdown": -0.1680225052918683,
    "win_rate": 0.3163265306122449,
    "total_trades": 98,
    "winning_trades_count": 31,
    "losing_trades_count": 18,
    "benchmark_return": 0.882978723404255,
    "benchmark_annual_return": 0.3052272130286313,
    "benchmark_sharpe": 0.9056169339207115,
    "benchmark_max_drawdown": -0.23241590214067315,
    "excess_return": 0,
    "information_ratio": -0.2034708035364469,
    "data_points": 730,
    "backtest_date": "2026-03-01 13:12:48"
  },
  {
    "stock_code": "1330.HK",
    "stock_name": "绿色动力环保",
    "total_return": 2.3037887051556165,
    "annual_return": 0.7963714042513241,
    "final_capital": 330378.87051556166,
    "sharpe_ratio": 1.6834501711265408,
    "sortino_ratio": 2.8452139861513084,
    "max_drawdown": -0.11435368789015748,
    "win_rate": 0.30612244897959184,
    "total_trades": 98,
    "winning_trades_count": 30,
    "losing_trades_count": 19,
    "benchmark_return": 1.1178707224334605,
    "benchmark_annual_return": 0.3864244472609493,
    "benchmark_sharpe": 0.9039795451043812,
    "benchmark_max_drawdown": -0.2585034013605444,
    "excess_return": 0,
    "information_ratio": 0.6839074449724362,
    "data_points": 730,
    "backtest_date": "2026-03-01 13:12:48"
  },
  {
    "stock_code": "1347.HK",
    "stock_name": "华虹半导体",
    "total_return": 2.414196144602914,
    "annual_return": 0.8345369388750814,
    "final_capital": 341419.6144602914,
    "sharpe_ratio": 1.3003796801519203,
    "sortino_ratio": 2.2572138833320206,
    "max_drawdown": -0.3205412929894047,
    "win_rate": 0.3717948717948718,
    "total_trades": 78,
    "winning_trades_count": 29,
    "losing_trades_count": 10,
    "benchmark_return": 2.0093312597200623,
    "benchmark_annual_return": 0.6945836453353301,
    "benchmark_sharpe": 0.8686184380676593,
    "benchmark_max_drawdown": -0.634782608695652,
    "excess_return": 0,
    "information_ratio": -0.2046813811135813,
    "data_points": 730,
    "backtest_date": "2026-03-01 13:12:48"
  },
  {
    "stock_code": "1398.HK",
    "stock_name": "工商银行",
    "total_return": 0.86347809336131,
    "annual_return": 0.2984862544952676,
    "final_capital": 186347.809336131,
    "sharpe_ratio": 1.6297184919099486,
    "sortino_ratio": 2.610015485921947,
    "max_drawdown": -0.10930867113646466,
    "win_rate": 0.34210526315789475,
    "total_trades": 76,
    "winning_trades_count": 26,
    "losing_trades_count": 12,
    "benchmark_return": 0.5504807692307694,
    "benchmark_annual_return": 0.190289648622982,
    "benchmark_sharpe": 0.6774623272299112,
    "benchmark_max_drawdown": -0.28051391862955044,
    "excess_return": 0,
    "information_ratio": 0.2176032112930224,
    "data_points": 730,
    "backtest_date": "2026-03-01 13:12:48"
  },
  {
    "stock_code": "1810.HK",
    "stock_name": "小米集团-W",
    "total_return": 1.2943617991509118,
    "annual_return": 0.4474337083484633,
    "final_capital": 229436.17991509117,
    "sharpe_ratio": 1.5606192719394956,
    "sortino_ratio": 3.127698263383112,
    "max_drawdown": -0.09650524295188499,
    "win_rate": 0.37142857142857144,
    "total_trades": 70,
    "winning_trades_count": 26,
    "losing_trades_count": 9,
    "benchmark_return": 2.0242634315424612,
    "benchmark_annual_return": 0.6997453837430729,
    "benchmark_sharpe": 1.0741562697036484,
    "benchmark_max_drawdown": -0.4354114713216948,
    "excess_return": 0,
    "information_ratio": -0.4445077174386448,
    "data_points": 730,
    "backtest_date": "2026-03-01 13:12:48"
  },
  {
    "stock_code": "2269.HK",
    "stock_name": "药明生物",
    "total_return": 1.4802532374934163,
    "annual_return": 0.511692477158218,
    "final_capital": 248025.32374934162,
    "sharpe_ratio": 0.9453950920278501,
    "sortino_ratio": 1.2888343499878694,
    "max_drawdown": -0.6142002059347004,
    "win_rate": 0.2672413793103448,
    "total_trades": 116,
    "winning_trades_count": 31,
    "losing_trades_count": 27,
    "benchmark_return": -0.24540337711069427,
    "benchmark_annual_return": -0.084830797025919,
    "benchmark_sharpe": 0.15197297785246983,
    "benchmark_max_drawdown": -0.8127737226277371,
    "excess_return": 0,
    "information_ratio": 0.5444558964545091,
    "data_points": 730,
    "backtest_date": "2026-03-01 13:12:48"
  },
  {
    "stock_code": "2533.HK",
    "stock_name": "黑芝麻智能",
    "total_return": 0.28534166875861044,
    "annual_return": 0.1887299226434904,
    "final_capital": 128534.16687586105,
    "sharpe_ratio": 0.559001145160808,
    "sortino_ratio": 0.7594130851837251,
    "max_drawdown": -0.42678761977518465,
    "win_rate": 0.28125,
    "total_trades": 64,
    "winning_trades_count": 18,
    "losing_trades_count": 14,
    "benchmark_return": -0.07090464547677257,
    "benchmark_annual_return": -0.046897560787786584,
    "benchmark_sharpe": 0.33317796455100923,
    "benchmark_max_drawdown": -0.6092783505154636,
    "excess_return": 0,
    "information_ratio": 0.07310824119934335,
    "data_points": 382,
    "backtest_date": "2026-03-01 13:12:48"
  },
  {
    "stock_code": "2800.HK",
    "stock_name": "盈富基金",
    "total_return": 0.872231956133718,
    "annual_return": 0.3015122811326432,
    "final_capital": 187223.1956133718,
    "sharpe_ratio": 1.273049622643345,
    "sortino_ratio": 1.692070014306826,
    "max_drawdown": -0.13582455533764537,
    "win_rate": 0.30158730158730157,
    "total_trades": 126,
    "winning_trades_count": 38,
    "losing_trades_count": 25,
    "benchmark_return": 0.3504016064257026,
    "benchmark_annual_return": 0.12112648123357621,
    "benchmark_sharpe": 0.47177181699049137,
    "benchmark_max_drawdown": -0.2811607992388199,
    "excess_return": 0,
    "information_ratio": 0.5765571854913464,
    "data_points": 730,
    "backtest_date": "2026-03-01 13:12:48"
  },
  {
    "stock_code": "3690.HK",
    "stock_name": "美团-W",
    "total_return": 0.7728323737720085,
    "annual_return": 0.26715193167427453,
    "final_capital": 177283.23737720086,
    "sharpe_ratio": 1.1177102549463367,
    "sortino_ratio": 2.0075460224026886,
    "max_drawdown": -0.09356509474711151,
    "win_rate": 0.30357142857142855,
    "total_trades": 56,
    "winning_trades_count": 17,
    "losing_trades_count": 11,
    "benchmark_return": -0.37093023255813956,
    "benchmark_annual_return": -0.1282227964398507,
    "benchmark_sharpe": -0.12736796566410952,
    "benchmark_max_drawdown": -0.6230084348641048,
    "excess_return": 0,
    "information_ratio": 0.5622061707987288,
    "data_points": 730,
    "backtest_date": "2026-03-01 13:12:48"
  },
  {
    "stock_code": "3968.HK",
    "stock_name": "招商银行",
    "total_return": 0.775475471897709,
    "annual_return": 0.2680655952238994,
    "final_capital": 177547.5471897709,
    "sharpe_ratio": 1.477626448303374,
    "sortino_ratio": 3.066796863644655,
    "max_drawdown": -0.0949627595244006,
    "win_rate": 0.328125,
    "total_trades": 64,
    "winning_trades_count": 21,
    "losing_trades_count": 11,
    "benchmark_return": 0.2149253731343284,
    "benchmark_annual_return": 0.07429519071310117,
    "benchmark_sharpe": 0.30987836023385074,
    "benchmark_max_drawdown": -0.4159713945172829,
    "excess_return": 0,
    "information_ratio": 0.2470057818669604,
    "data_points": 730,
    "backtest_date": "2026-03-01 13:12:48"
  },
  {
    "stock_code": "6682.HK",
    "stock_name": "第四范式",
    "total_return": -0.020835130599995318,
    "annual_return": -0.008869008295943953,
    "final_capital": 97916.48694000047,
    "sharpe_ratio": 0.06041866790464329,
    "sortino_ratio": 0.08455981920900892,
    "max_drawdown": -0.4011516526875175,
    "win_rate": 0.32,
    "total_trades": 50,
    "winning_trades_count": 16,
    "losing_trades_count": 9,
    "benchmark_return": -0.32,
    "benchmark_annual_return": -0.1362162162162162,
    "benchmark_sharpe": 0.15728102829341617,
    "benchmark_max_drawdown": -0.7344370860927151,
    "excess_return": 0,
    "information_ratio": -0.1453573130994257,
    "data_points": 593,
    "backtest_date": "2026-03-01 13:12:48"
  },
  {
    "stock_code": "9660.HK",
    "stock_name": "地平线机器人",
    "total_return": 4.5688566083297095,
    "annual_return": 3.488945046360869,
    "final_capital": 556885.660832971,
    "sharpe_ratio": 2.9900757287937347,
    "sortino_ratio": 6.857182333301373,
    "max_drawdown": -0.16043370447245536,
    "win_rate": 0.4166666666666667,
    "total_trades": 36,
    "winning_trades_count": 15,
    "losing_trades_count": 3,
    "benchmark_return": 1.0024390243902441,
    "benchmark_annual_return": 0.7654988913525501,
    "benchmark_sharpe": 1.0778878711145254,
    "benchmark_max_drawdown": -0.5290519877675844,
    "excess_return": 0,
    "information_ratio": 1.269047118835036,
    "data_points": 331,
    "backtest_date": "2026-03-01 13:12:48"
  },
  {
    "stock_code": "9988.HK",
    "stock_name": "阿里巴巴-SW",
    "total_return": 1.4434944878670104,
    "annual_return": 0.49898574889229985,
    "final_capital": 244349.44878670105,
    "sharpe_ratio": 1.8989335578894884,
    "sortino_ratio": 4.3897332392991615,
    "max_drawdown": -0.09975637313237512,
    "win_rate": 0.3275862068965517,
    "total_trades": 58,
    "winning_trades_count": 19,
    "losing_trades_count": 10,
    "benchmark_return": 0.7165165165165166,
    "benchmark_annual_return": 0.24768472175879586,
    "benchmark_sharpe": 0.5998837292322818,
    "benchmark_max_drawdown": -0.34810756972111606,
    "excess_return": 0,
    "information_ratio": 0.10268666618914324,
    "data_points": 730,
    "backtest_date": "2026-03-01 13:12:48"
  },
  {
    "stock_code": "1211.HK",
    "stock_name": "比亚迪股份",
    "total_return": 0.583305792575007,
    "annual_return": 0.20163657027284193,
    "final_capital": 158330.5792575007,
    "sharpe_ratio": 1.2000001980335921,
    "sortino_ratio": 3.3991619743606383,
    "max_drawdown": -0.07052233799203465,
    "win_rate": 0.3409090909090909,
    "total_trades": 44,
    "winning_trades_count": 15,
    "losing_trades_count": 7,
    "benchmark_return": -0.52525,
    "benchmark_annual_return": -0.1815679012345679,
    "benchmark_sharpe": -0.11074454470388477,
    "benchmark_max_drawdown": -0.8065348237317285,
    "excess_return": 0,
    "information_ratio": 0.38960791360643465,
    "data_points": 730,
    "backtest_date": "2026-03-01 13:12:48"
  },
  {
    "stock_code": "1299.HK",
    "stock_name": "友邦保险",
    "total_return": 0.7375206672164714,
    "annual_return": 0.254945415827916,
    "final_capital": 173752.06672164713,
    "sharpe_ratio": 1.0175915488255445,
    "sortino_ratio": 1.4811402694934883,
    "max_drawdown": -0.1812967101671972,
    "win_rate": 0.3170731707317073,
    "total_trades": 82,
    "winning_trades_count": 26,
    "losing_trades_count": 15,
    "benchmark_return": 0.0278271166370633,
    "benchmark_annual_return": 0.009619250195528053,
    "benchmark_sharpe": 0.12357683669835297,
    "benchmark_max_drawdown": -0.4644935972060533,
    "excess_return": 0,
    "information_ratio": 0.5946050361986359,
    "data_points": 730,
    "backtest_date": "2026-03-01 13:12:48"
  }
]