{
  "lgbm_20d": {
    "model_type": "lgbm",
    "horizon": 20,
    "accuracy": 0.6021490933512423,
    "std": 0.05740062238631057,
    "timestamp": "2026-02-20 19:43:30"
  },
  "gbdt_20d": {
    "model_type": "gbdt",
    "horizon": 20,
    "accuracy": 0.5869448183041722,
    "std": 0.04266168772692243,
    "timestamp": "2026-02-20 19:45:11"
  },
  "lgbm_1d": {
    "model_type": "lgbm",
    "horizon": 1,
    "accuracy": 0.5188144329896908,
    "std": 0.023318689765500035,
    "timestamp": "2026-02-17 14:24:00"
  },
  "catboost_20d": {
    "model_type": "catboost",
    "horizon": 20,
    "accuracy": 0.6142902307935505,
    "std": 0.017122676288968904,
    "timestamp": "2026-02-20 19:47:53"
  }
}